{
  "Title": "Security update for conmon",
  "Tracking": {
    "ID": "SUSE-SU-2023:1796-1",
    "Status": "Final",
    "Version": "1",
    "InitialReleaseDate": "2023-04-07T09:06:51Z",
    "CurrentReleaseDate": "2023-04-07T09:06:51Z",
    "RevisionHistory": [
      {
        "Number": "1",
        "Date": "2023-04-07T09:06:51Z",
        "Description": "current"
      }
    ]
  },
  "Notes": [
    {
      "Text": "Security update for conmon",
      "Title": "Topic",
      "Type": "Summary"
    },
    {
      "Text": "This update for conmon fixes the following issues:\n\n- rebuild against supported go 1.19 (bsc#1209307)\n- no functional changes.\n",
      "Title": "Details",
      "Type": "General"
    },
    {
      "Text": "The CVRF data is provided by SUSE under the Creative Commons License 4.0 with Attribution (CC-BY-4.0).",
      "Title": "Terms of Use",
      "Type": "Legal Disclaimer"
    },
    {
      "Text": "Container rancher/elemental-teal-rt/5.4:latest-2023-1796,Container rancher/elemental-teal/5.4:latest-2023-1796,SUSE-2023-1796,SUSE-SLE-Micro-5.3-2023-1796,SUSE-SLE-Module-Containers-15-SP4-2023-1796,openSUSE-Leap-Micro-5.3-2023-1796,openSUSE-SLE-15.4-2023-1796",
      "Title": "Patchnames",
      "Type": "Details"
    }
  ],
  "ProductTree": {
    "Relationships": [
      {
        "ProductReference": "conmon-2.1.5-150400.3.6.1",
        "RelatesToProductReference": "Container rancher/elemental-teal-rt/5.4:latest",
        "RelationType": "Default Component Of"
      },
      {
        "ProductReference": "conmon-2.1.5-150400.3.6.1",
        "RelatesToProductReference": "Container rancher/elemental-teal/5.4:latest",
        "RelationType": "Default Component Of"
      },
      {
        "ProductReference": "conmon-2.1.5-150400.3.6.1",
        "RelatesToProductReference": "SUSE Linux Enterprise Micro 5.3",
        "RelationType": "Default Component Of"
      },
      {
        "ProductReference": "conmon-2.1.5-150400.3.6.1",
        "RelatesToProductReference": "SUSE Linux Enterprise Module for Containers 15 SP4",
        "RelationType": "Default Component Of"
      },
      {
        "ProductReference": "conmon-2.1.5-150400.3.6.1",
        "RelatesToProductReference": "openSUSE Leap 15.4",
        "RelationType": "Default Component Of"
      },
      {
        "ProductReference": "conmon-2.1.5-150400.3.6.1",
        "RelatesToProductReference": "openSUSE Leap Micro 5.3",
        "RelationType": "Default Component Of"
      }
    ]
  },
  "References": [
    {
      "URL": "https://www.suse.com/support/update/announcement/2023/suse-su-20231796-1/",
      "Description": "Link for SUSE-SU-2023:1796-1"
    },
    {
      "URL": "https://lists.suse.com/pipermail/sle-security-updates/2023-April/014429.html",
      "Description": "E-Mail link for SUSE-SU-2023:1796-1"
    },
    {
      "URL": "https://www.suse.com/support/security/rating/",
      "Description": "SUSE Security Ratings"
    },
    {
      "URL": "https://bugzilla.suse.com/1209307",
      "Description": "SUSE Bug 1209307"
    }
  ],
  "Vulnerabilities": null
}