{
  "Title": "Security update for conmon",
  "Tracking": {
    "ID": "SUSE-SU-2023:4101-1",
    "Status": "Final",
    "Version": "1",
    "InitialReleaseDate": "2023-10-17T13:13:59Z",
    "CurrentReleaseDate": "2023-10-17T13:13:59Z",
    "RevisionHistory": [
      {
        "Number": "1",
        "Date": "2023-10-17T13:13:59Z",
        "Description": "current"
      }
    ]
  },
  "Notes": [
    {
      "Text": "Security update for conmon",
      "Title": "Topic",
      "Type": "Summary"
    },
    {
      "Text": "This update for conmon fixes the following issues:\n\nconmon is rebuilt with the current stable release go1.21 (bsc#1215806)\n",
      "Title": "Details",
      "Type": "General"
    },
    {
      "Text": "The CVRF data is provided by SUSE under the Creative Commons License 4.0 with Attribution (CC-BY-4.0).",
      "Title": "Terms of Use",
      "Type": "Legal Disclaimer"
    },
    {
      "Text": "SUSE-2023-4101,SUSE-SLE-Product-HPC-15-SP3-ESPOS-2023-4101,SUSE-SLE-Product-HPC-15-SP3-LTSS-2023-4101,SUSE-SLE-Product-SLES-15-SP3-LTSS-2023-4101,SUSE-SLE-Product-SLES_SAP-15-SP3-2023-4101,SUSE-SUSE-MicroOS-5.1-2023-4101,SUSE-SUSE-MicroOS-5.2-2023-4101,SUSE-Storage-7.1-2023-4101",
      "Title": "Patchnames",
      "Type": "Details"
    }
  ],
  "ProductTree": {
    "Relationships": [
      {
        "ProductReference": "conmon-2.1.5-150300.8.14.1",
        "RelatesToProductReference": "SUSE Enterprise Storage 7.1",
        "RelationType": "Default Component Of"
      },
      {
        "ProductReference": "conmon-2.1.5-150300.8.14.1",
        "RelatesToProductReference": "SUSE Linux Enterprise High Performance Computing 15 SP3-ESPOS",
        "RelationType": "Default Component Of"
      },
      {
        "ProductReference": "conmon-2.1.5-150300.8.14.1",
        "RelatesToProductReference": "SUSE Linux Enterprise High Performance Computing 15 SP3-LTSS",
        "RelationType": "Default Component Of"
      },
      {
        "ProductReference": "conmon-2.1.5-150300.8.14.1",
        "RelatesToProductReference": "SUSE Linux Enterprise Micro 5.1",
        "RelationType": "Default Component Of"
      },
      {
        "ProductReference": "conmon-2.1.5-150300.8.14.1",
        "RelatesToProductReference": "SUSE Linux Enterprise Micro 5.2",
        "RelationType": "Default Component Of"
      },
      {
        "ProductReference": "conmon-2.1.5-150300.8.14.1",
        "RelatesToProductReference": "SUSE Linux Enterprise Server 15 SP3-LTSS",
        "RelationType": "Default Component Of"
      },
      {
        "ProductReference": "conmon-2.1.5-150300.8.14.1",
        "RelatesToProductReference": "SUSE Linux Enterprise Server for SAP Applications 15 SP3",
        "RelationType": "Default Component Of"
      }
    ]
  },
  "References": [
    {
      "URL": "https://www.suse.com/support/update/announcement/2023/suse-su-20234101-1/",
      "Description": "Link for SUSE-SU-2023:4101-1"
    },
    {
      "URL": "https://lists.suse.com/pipermail/sle-security-updates/2023-October/016710.html",
      "Description": "E-Mail link for SUSE-SU-2023:4101-1"
    },
    {
      "URL": "https://www.suse.com/support/security/rating/",
      "Description": "SUSE Security Ratings"
    },
    {
      "URL": "https://bugzilla.suse.com/1215806",
      "Description": "SUSE Bug 1215806"
    }
  ],
  "Vulnerabilities": null
}