{
  "id": "BRSA-nqsb04mze5ei",
  "title": "modules-neuron support ended",
  "issued": {
    "date": "2026-05-28T23:18:30Z"
  },
  "updated": {
    "date": "2026-05-28T23:18:30Z"
  },
  "severity": "low",
  "description": "modules-neuron sub-package is no longer included in Bottlerocket. All users must upgrade to a version of the OS that does not include this package.",
  "packages": [
    {
      "name": "kernel-6.12-modules-neuron",
      "epoch": "1",
      "version": "6.12.77",
      "release": "1.1779997967.64782dc8.br1",
      "arch": "x86_64"
    },
    {
      "name": "kernel-6.1-modules-neuron",
      "epoch": "1",
      "version": "6.1.166",
      "release": "1.1779997967.64782dc8.br1",
      "arch": "x86_64"
    },
    {
      "name": "kernel-6.18-modules-neuron",
      "epoch": "1",
      "version": "6.18.16",
      "release": "1.1779997967.64782dc8.br1",
      "arch": "x86_64"
    },
    {
      "name": "bottlerocket-kernel-6.12-modules-neuron",
      "epoch": "1",
      "version": "6.12.77",
      "release": "1.1779997967.64782dc8.br1",
      "arch": "x86_64"
    },
    {
      "name": "bottlerocket-kernel-6.1-modules-neuron",
      "epoch": "1",
      "version": "6.1.166",
      "release": "1.1779997967.64782dc8.br1",
      "arch": "x86_64"
    },
    {
      "name": "bottlerocket-kernel-6.18-modules-neuron",
      "epoch": "1",
      "version": "6.18.16",
      "release": "1.1779997967.64782dc8.br1",
      "arch": "x86_64"
    },
    {
      "name": "kernel-6.12-modules-neuron",
      "epoch": "1",
      "version": "6.12.77",
      "release": "1.1779997967.64782dc8.br1",
      "arch": "aarch64"
    },
    {
      "name": "kernel-6.1-modules-neuron",
      "epoch": "1",
      "version": "6.1.166",
      "release": "1.1779997967.64782dc8.br1",
      "arch": "aarch64"
    },
    {
      "name": "kernel-6.18-modules-neuron",
      "epoch": "1",
      "version": "6.18.16",
      "release": "1.1779997967.64782dc8.br1",
      "arch": "aarch64"
    },
    {
      "name": "bottlerocket-kernel-6.12-modules-neuron",
      "epoch": "1",
      "version": "6.12.77",
      "release": "1.1779997967.64782dc8.br1",
      "arch": "aarch64"
    },
    {
      "name": "bottlerocket-kernel-6.1-modules-neuron",
      "epoch": "1",
      "version": "6.1.166",
      "release": "1.1779997967.64782dc8.br1",
      "arch": "aarch64"
    },
    {
      "name": "bottlerocket-kernel-6.18-modules-neuron",
      "epoch": "1",
      "version": "6.18.16",
      "release": "1.1779997967.64782dc8.br1",
      "arch": "aarch64"
    }
  ],
  "references": [
    {
      "href": "https://github.com/bottlerocket-os/bottlerocket-kernel-kit/blob/develop/advisories/6.0.0/BRSA-nqsb04mze5ei.toml",
      "id": "BRSA-nqsb04mze5ei",
      "type": "brsa"
    }
  ]
}