{
  "Identifier": "GMS-2016-23",
  "PackageSlug": "npm/npm",
  "Title": "False Positive",
  "Description": "This advisory has been marked as a False Positive and has been removed.",
  "Date": "2025-08-19",
  "Pubdate": "2016-04-18",
  "AffectedRange": "\u003c0",
  "FixedVersions": [],
  "AffectedVersions": "All versions before 0",
  "NotImpacted": "",
  "Solution": "Unfortunately, there is no solution available yet.",
  "Urls": [
    "http://blog.npmjs.org/post/142036323955/fixing-a-bearer-token-vulnerability",
    "https://nodejs.org/en/blog/vulnerability/npm-tokens-leak-march-2016/",
    "https://www.npmjs.com/settings/tokens"
  ],
  "CvssV2": "",
  "CvssV3": "",
  "UUID": "4cb639ca-5f18-4c73-91f8-1b5db9a10866"
}