{
  "Title": "Security update for ovmf",
  "Tracking": {
    "ID": "SUSE-SU-2021:2119-1",
    "Status": "Final",
    "Version": "1",
    "InitialReleaseDate": "2021-06-22T11:57:33Z",
    "CurrentReleaseDate": "2021-06-22T11:57:33Z",
    "RevisionHistory": [
      {
        "Number": "1",
        "Date": "2021-06-22T11:57:33Z",
        "Description": "current"
      }
    ]
  },
  "Notes": [
    {
      "Text": "Security update for ovmf",
      "Title": "Topic",
      "Type": "Summary"
    },
    {
      "Text": "This update for ovmf fixes the following issues:\n\n- Fixed a possible  buffer overflow in IScsiDxe (bsc#1186151)\n",
      "Title": "Details",
      "Type": "General"
    },
    {
      "Text": "The CVRF data is provided by SUSE under the Creative Commons License 4.0 with Attribution (CC-BY-4.0).",
      "Title": "Terms of Use",
      "Type": "Legal Disclaimer"
    },
    {
      "Text": "HPE-Helion-OpenStack-8-2021-2119,SUSE-2021-2119,SUSE-OpenStack-Cloud-8-2021-2119,SUSE-OpenStack-Cloud-Crowbar-8-2021-2119,SUSE-SLE-SAP-12-SP3-2021-2119,SUSE-SLE-SERVER-12-SP3-2021-2119,SUSE-SLE-SERVER-12-SP3-BCL-2021-2119",
      "Title": "Patchnames",
      "Type": "Details"
    }
  ],
  "ProductTree": {
    "Relationships": [
      {
        "ProductReference": "ovmf-2017+git1492060560.b6d11d7c46-4.44.1",
        "RelatesToProductReference": "HPE Helion OpenStack 8",
        "RelationType": "Default Component Of"
      },
      {
        "ProductReference": "ovmf-tools-2017+git1492060560.b6d11d7c46-4.44.1",
        "RelatesToProductReference": "HPE Helion OpenStack 8",
        "RelationType": "Default Component Of"
      },
      {
        "ProductReference": "qemu-ovmf-x86_64-2017+git1492060560.b6d11d7c46-4.44.1",
        "RelatesToProductReference": "HPE Helion OpenStack 8",
        "RelationType": "Default Component Of"
      },
      {
        "ProductReference": "ovmf-2017+git1492060560.b6d11d7c46-4.44.1",
        "RelatesToProductReference": "SUSE Linux Enterprise Server 12 SP3-BCL",
        "RelationType": "Default Component Of"
      },
      {
        "ProductReference": "ovmf-tools-2017+git1492060560.b6d11d7c46-4.44.1",
        "RelatesToProductReference": "SUSE Linux Enterprise Server 12 SP3-BCL",
        "RelationType": "Default Component Of"
      },
      {
        "ProductReference": "qemu-ovmf-x86_64-2017+git1492060560.b6d11d7c46-4.44.1",
        "RelatesToProductReference": "SUSE Linux Enterprise Server 12 SP3-BCL",
        "RelationType": "Default Component Of"
      },
      {
        "ProductReference": "ovmf-2017+git1492060560.b6d11d7c46-4.44.1",
        "RelatesToProductReference": "SUSE Linux Enterprise Server 12 SP3-LTSS",
        "RelationType": "Default Component Of"
      },
      {
        "ProductReference": "ovmf-tools-2017+git1492060560.b6d11d7c46-4.44.1",
        "RelatesToProductReference": "SUSE Linux Enterprise Server 12 SP3-LTSS",
        "RelationType": "Default Component Of"
      },
      {
        "ProductReference": "qemu-ovmf-x86_64-2017+git1492060560.b6d11d7c46-4.44.1",
        "RelatesToProductReference": "SUSE Linux Enterprise Server 12 SP3-LTSS",
        "RelationType": "Default Component Of"
      },
      {
        "ProductReference": "qemu-uefi-aarch64-2017+git1492060560.b6d11d7c46-4.44.1",
        "RelatesToProductReference": "SUSE Linux Enterprise Server 12 SP3-LTSS",
        "RelationType": "Default Component Of"
      },
      {
        "ProductReference": "ovmf-2017+git1492060560.b6d11d7c46-4.44.1",
        "RelatesToProductReference": "SUSE Linux Enterprise Server for SAP Applications 12 SP3",
        "RelationType": "Default Component Of"
      },
      {
        "ProductReference": "ovmf-tools-2017+git1492060560.b6d11d7c46-4.44.1",
        "RelatesToProductReference": "SUSE Linux Enterprise Server for SAP Applications 12 SP3",
        "RelationType": "Default Component Of"
      },
      {
        "ProductReference": "qemu-ovmf-x86_64-2017+git1492060560.b6d11d7c46-4.44.1",
        "RelatesToProductReference": "SUSE Linux Enterprise Server for SAP Applications 12 SP3",
        "RelationType": "Default Component Of"
      },
      {
        "ProductReference": "ovmf-2017+git1492060560.b6d11d7c46-4.44.1",
        "RelatesToProductReference": "SUSE OpenStack Cloud 8",
        "RelationType": "Default Component Of"
      },
      {
        "ProductReference": "ovmf-tools-2017+git1492060560.b6d11d7c46-4.44.1",
        "RelatesToProductReference": "SUSE OpenStack Cloud 8",
        "RelationType": "Default Component Of"
      },
      {
        "ProductReference": "qemu-ovmf-x86_64-2017+git1492060560.b6d11d7c46-4.44.1",
        "RelatesToProductReference": "SUSE OpenStack Cloud 8",
        "RelationType": "Default Component Of"
      },
      {
        "ProductReference": "ovmf-2017+git1492060560.b6d11d7c46-4.44.1",
        "RelatesToProductReference": "SUSE OpenStack Cloud Crowbar 8",
        "RelationType": "Default Component Of"
      },
      {
        "ProductReference": "ovmf-tools-2017+git1492060560.b6d11d7c46-4.44.1",
        "RelatesToProductReference": "SUSE OpenStack Cloud Crowbar 8",
        "RelationType": "Default Component Of"
      },
      {
        "ProductReference": "qemu-ovmf-x86_64-2017+git1492060560.b6d11d7c46-4.44.1",
        "RelatesToProductReference": "SUSE OpenStack Cloud Crowbar 8",
        "RelationType": "Default Component Of"
      }
    ]
  },
  "References": [
    {
      "URL": "https://www.suse.com/support/update/announcement/2021/suse-su-20212119-1/",
      "Description": "Link for SUSE-SU-2021:2119-1"
    },
    {
      "URL": "https://lists.suse.com/pipermail/sle-security-updates/2021-June/009071.html",
      "Description": "E-Mail link for SUSE-SU-2021:2119-1"
    },
    {
      "URL": "https://www.suse.com/support/security/rating/",
      "Description": "SUSE Security Ratings"
    },
    {
      "URL": "https://bugzilla.suse.com/1186151",
      "Description": "SUSE Bug 1186151"
    }
  ],
  "Vulnerabilities": null
}