{
  "Identifier": "GMS-2015-38",
  "PackageSlug": "npm/secure-compare",
  "Title": "Insecure Comparison",
  "Description": "Secure-compare does not actually compare two strings properly. compare actually compares the first argument with itself, meaning the check passes for any two strings of the same length.",
  "Date": "2015-10-24",
  "Pubdate": "2015-10-24",
  "AffectedRange": "\u003c=3.0.0",
  "FixedVersions": [],
  "AffectedVersions": "All versions up to 3.0.0",
  "NotImpacted": "",
  "Solution": "Upgrade to secure-compare 3.0.1 or greater.",
  "Urls": [
    "https://github.com/vdemedes/secure-compare/pull/1"
  ],
  "CvssV2": "",
  "CvssV3": "",
  "UUID": "d206158e-37e8-400c-8eda-01cf6f6a750d"
}