{
  "Identifier": "2014-05-20",
  "PackageSlug": "packagist/illuminate/database",
  "Title": "Improperly Controlled Modification of Dynamically-Determined Object Attributes",
  "Description": "Risk of mass-assignment vulnerabilities.",
  "Date": "2014-05-20",
  "Pubdate": "2014-05-20",
  "AffectedRange": "\u003e=4.0.0,\u003c4.0.99||\u003e=4.1.0,\u003c4.1.29",
  "FixedVersions": [
    "4.1.29"
  ],
  "AffectedVersions": "All versions starting from 4.0.0 before 4.0.99, all versions starting from 4.1.0 before 4.1.29",
  "NotImpacted": "All versions before 4.0.0, all versions starting from 4.0.99 before 4.1.0, all versions starting from 4.1.29",
  "Solution": "Upgrade to version 4.1.29 or above.",
  "Urls": [
    "https://laravel.com/docs/5.1/upgrade#upgrade-4.1.29"
  ],
  "CvssV2": "",
  "CvssV3": "",
  "UUID": "726be006-4cb3-495f-a281-b9e82e80627f"
}