{
  "Title": "Security update for govulncheck-vulndb",
  "Tracking": {
    "ID": "SUSE-SU-2025:4220-1",
    "Status": "Final",
    "Version": "1",
    "InitialReleaseDate": "2025-11-25T08:02:35Z",
    "CurrentReleaseDate": "2025-11-25T08:02:35Z",
    "RevisionHistory": [
      {
        "Number": "1",
        "Date": "2025-11-25T08:02:35Z",
        "Description": "current"
      }
    ]
  },
  "Notes": [
    {
      "Text": "Security update for govulncheck-vulndb",
      "Title": "Topic",
      "Type": "Summary"
    },
    {
      "Text": "This update for govulncheck-vulndb fixes the following issues:\n\n- Update to version 0.0.20251120T220319 2025-11-20T22:03:19Z. (jsc#PED-11136):\n\n  * GO-2023-2331 \n  * GO-2024-2587 \n  * GO-2025-3770 \n  * GO-2025-4007\n  * GO-2025-4134 \n  * GO-2025-4135 \n\n- Update to version 0.0.20251118T154415 2025-11-18T15:44:15Z. (jsc#PED-11136):\n \n  * GO-2025-4025 \n  * GO-2025-4090 \n  * GO-2025-4091 \n  * GO-2025-4093 \n  * GO-2025-4094 \n  * GO-2025-4095 \n  * GO-2025-4096 \n  * GO-2025-4097 \n  * GO-2025-4098 \n  * GO-2025-4099 \n  * GO-2025-4100 \n  * GO-2025-4101 \n  * GO-2025-4102 \n  * GO-2025-4103 \n  * GO-2025-4104 \n  * GO-2025-4105 \n  * GO-2025-4106 \n  * GO-2025-4107 \n  * GO-2025-4108 \n  * GO-2025-4109 \n  * GO-2025-4110 \n  * GO-2025-4111 \n  * GO-2025-4112 \n  * GO-2025-4113 \n  * GO-2025-4114 \n  * GO-2025-4115 \n  * GO-2025-4117 \n  * GO-2025-4118 \n  * GO-2025-4119 \n  * GO-2025-4120 \n  * GO-2025-4121 \n  * GO-2025-4122 \n  * GO-2025-4123 \n  * GO-2025-4124 \n  * GO-2025-4125 \n  * GO-2025-4126 \n  * GO-2025-4127 \n  * GO-2025-4128 \n  * GO-2025-4129 \n  * GO-2025-4130\n  * GO-2025-4131\n\n- Update to version 0.0.20251113T211203 2025-11-13T21:12:03Z (jsc#PED-11136):\n\n  * GO-2025-4116\n",
      "Title": "Details",
      "Type": "General"
    },
    {
      "Text": "The CVRF data is provided by SUSE under the Creative Commons License 4.0 with Attribution (CC-BY-4.0).",
      "Title": "Terms of Use",
      "Type": "Legal Disclaimer"
    },
    {
      "Text": "SUSE-2025-4220,SUSE-SLE-Module-Packagehub-Subpackages-15-SP6-2025-4220,openSUSE-SLE-15.6-2025-4220",
      "Title": "Patchnames",
      "Type": "Details"
    }
  ],
  "ProductTree": {
    "Relationships": null
  },
  "References": [
    {
      "URL": "https://www.suse.com/support/update/announcement/2025/suse-su-20254220-1/",
      "Description": "Link for SUSE-SU-2025:4220-1"
    },
    {
      "URL": "https://lists.suse.com/pipermail/sle-security-updates/2025-November/023355.html",
      "Description": "E-Mail link for SUSE-SU-2025:4220-1"
    },
    {
      "URL": "https://www.suse.com/support/security/rating/",
      "Description": "SUSE Security Ratings"
    }
  ],
  "Vulnerabilities": null
}